[
  {
    "title": "Hoshi – Bonjour Docteur Tour",
    "date": "2027-11-18",
    "date_fin": null,
    "time": "20:00",
    "cat": "concert",
    "venue": "Accor Arena, Paris (75012)",
    "notes": "Pop française. Accor Arena – Bercy. Date confirmée.\nhttps://www.accorarena.com/",
    "reminders": [
      "2w",
      "1w"
    ],
    "score": 40,
    "source": "accorarena.com",
    "match_reasons": [
      "genre_prefere: pop",
      "lieu_emblematique: Accor Arena",
      "proximite_dans_rayon: Paris"
    ],
    "image_url": null
  }
]