[
  {
    "title": "Rock en Seine 2027",
    "date": "2027-08-25",
    "date_fin": "2027-08-29",
    "time": "14:00",
    "cat": "concert",
    "venue": "Domaine National de Saint-Cloud (92)",
    "notes": "Festival rock/indie/pop. Date estimée / récurrent (dernier mercredi d'août). Line-up TBA. 23e édition attendue.\nhttps://www.rockenseine.com/",
    "reminders": [
      "1m",
      "2w"
    ],
    "score": 80,
    "source": "rockenseine.com",
    "match_reasons": [
      "festival",
      "genre_prefere: rock/indie/pop",
      "proximite_dans_rayon: ~10km Paris",
      "jour_prefere: vendredi/samedi/dimanche"
    ],
    "image_url": null
  },
  {
    "title": "Jazz à la Villette 2027",
    "date": "2027-08-27",
    "date_fin": "2027-09-05",
    "time": "19:00",
    "cat": "concert",
    "venue": "Philharmonie de Paris / Grande Halle de La Villette (75019)",
    "notes": "Festival jazz annuel récurrent. Date estimée (fin août-début sept). Line-up TBA.\nhttps://jazzalavillette.com/fr/",
    "reminders": [
      "1m",
      "2w"
    ],
    "score": 80,
    "source": "jazzalavillette.com",
    "match_reasons": [
      "festival",
      "genre_prefere: jazz/soul",
      "lieu_emblematique: Philharmonie de Paris",
      "lieu_prefere: Philharmonie de Paris"
    ],
    "image_url": null
  },
  {
    "title": "Paris Jazz Festival 2027",
    "date": "2027-06-27",
    "date_fin": "2027-09-05",
    "time": "15:00",
    "cat": "concert",
    "venue": "Parc Floral de Vincennes (75012)",
    "notes": "Concerts jazz gratuits les week-ends (entrée parc 2,50€). Date estimée / récurrent (fin juin–début sept). Line-up TBA.\nhttps://festivalsduparcfloral.paris/programmation/paris-jazz-festival/",
    "reminders": [
      "1w"
    ],
    "score": 75,
    "source": "festivalsduparcfloral.paris",
    "match_reasons": [
      "gratuit",
      "genre_prefere: jazz/world",
      "festival",
      "proximite_dans_rayon: Paris"
    ],
    "image_url": null
  }
]